{
  "project_info": {
    "project_number": "497229688858",
    "project_id": "finance-app-85342",
    "storage_bucket": "finance-app-85342.firebasestorage.app"
  },
  "client": [
    {
      "client_info": {
        "mobilesdk_app_id": "1:497229688858:android:b9162ffc8388fefdfba1a3",
        "android_client_info": {
          "package_name": "com.example.app"
        }
      },
      "oauth_client": [],
      "api_key": [
        {
          "current_key": "AIzaSyDJgPfBaBnjtrosEx-c182Dh395NllJrpg"
        }
      ],
      "services": {
        "appinvite_service": {
          "other_platform_oauth_client": []
        }
      }
    },
    {
      "client_info": {
        "mobilesdk_app_id": "1:497229688858:android:eb8500cd552fa356fba1a3",
        "android_client_info": {
          "package_name": "com.example.finance_app"
        }
      },
      "oauth_client": [],
      "api_key": [
        {
          "current_key": "AIzaSyDJgPfBaBnjtrosEx-c182Dh395NllJrpg"
        }
      ],
      "services": {
        "appinvite_service": {
          "other_platform_oauth_client": []
        }
      }
    }
  ],
  "configuration_version": "1"
}